tilesmith-0.1.1.dist-info/METADATA
tilesmith-0.1.1.dist-info/WHEEL
tilesmith-0.1.1.dist-info/licenses/LICENSE
tilesmith/__init__.py
tilesmith/hello.py
tilesmith-0.1.1.dist-info/RECORD
